{"classes":[{"id":"15.20.00","title":""}],"title":"","text":"Vejledning til Tilbud efter lov om en aktiv besk\u00e6ftigelsesindsats\nModtagere af kontanthj\u00e6lp og uddannelseshj\u00e6lp\nBlanket AB 101 Tilbud efter lov om en aktiv besk\u00e6ftigelsespolitik anvendes, n\u00e5r der gives tilbud efter lov om en aktiv\nbesk\u00e6ftigelsesindsats (besk\u00e6ftigelsesloven) om deltagelse\ni et af f\u00f8lgende tilbud:\n\u2022 Ordin\u00e6re uddannelsesforl\u00f8b\n(\u00a7 32, stk. 1, nr. 1)\n\u2022 \u00d8vrige uddannelser og kurser, samt s\u00e6rligt tilrettelagte\nprojekter og uddannelsesforl\u00f8b\n(\u00a7 32, stk. 1, nr. 2)\n\u2022 Virksomhedspraktik\n(\u00a7 42)\n\u2022 Nytteindsats\n(\u00a7 42a, b)\n\nR\u00e5dighedsforpligtigelse\nDu skal v\u00e6re aktivt arbejdss\u00f8gende og st\u00e5 til r\u00e5dighed for\nhenvist arbejde under deltagelse i et tilbud.\n\n5 708410 044922\n\nEfter den 1. januar 2018 er det obligatorisk at anvende den digitale l\u00f8sning p\u00e5 virk.dk n\u00e5r\ntilbuddet drejer sig om virksomhedspraktik efter kapitel 11 i lov om en aktiv besk\u00e6ftigelsesindsats. Blanketten vil derfor blive udfaset i l\u00f8bet af 2018 for s\u00e5 vidt ang\u00e5r virksomhedspraktik efter kapitel 11.\n\nJobcenteret kan i s\u00e6rlige tilf\u00e6lde fravige r\u00e5dighedsforpligtigelsen, hvis det sk\u00f8nnes, at tilbuddet medvirker til, at du\nkan opn\u00e5 fast besk\u00e6ftigelse. Det kan f.eks. v\u00e6re tilf\u00e6ldet,\nn\u00e5r der foreligger en klar aftale om et konkret job efter gennemf\u00f8relse af et bestemt uddannelsesforl\u00f8b.\n\nFerie\nDu har ogs\u00e5 i tilbuddet ret til at holde op til 4 ugers ferie, dog\nmaksimalt 2 uger ad gangen. Det kr\u00e6ver dog, at du har\nmodtaget hj\u00e6lp i sammenlagt 12 mdr. forud for feriens\nOplysningspligt\nafholdelse. Feriens placering skal aftales mellem dig og\nDu har pligt til at underrette jobcenteret om enhver \u00e6ndring jobcenteret.\ni dine personlige og \u00f8konomiske forhold, der kan have\nbetydning for retten til uddannelses- og kontanthj\u00e6lp og Ydelse\ndeltagelse i tilbuddet.\nUnder tilbuddet modtager du fortsat uddannelses- eller kontanthj\u00e6lp.\nTilbudsstedet\/arbejdspladsen har pligt til at give jobcenteret\noplysning om udeblivelse fra eller oph\u00f8r af tilbud.\nTavshedspligt\nI forbindelse med dit tilbudsforl\u00f8b i det offentlige er du p\u00e5lagt\nHvis du bliver syg, skal du hurtigst muligt give jobcenteret tavshedspligt efter forvaltningsloven og straffeloven. Hvis\nog\/eller arbejdsstedet besked. Kontaktperson vil ofte v\u00e6re du f\u00e5r kendskab til oplysninger af personlig eller fortrolig\nangivet p\u00e5 blanketten.\nkarakter, m\u00e5 du ikke give oplysningerne videre. S\u00e5fremt du\ner i tvivl om tavshedspligtens r\u00e6kkevidde, skal du rette henSanktioner ved udeblivelse eller afbrydelse af tilbuddet vendelse til din n\u00e6rmeste leder eller kontaktperson p\u00e5 tilUdebliver du uden rimelig grund fra et tilbud efter lov om budsstedet.\naktiv besk\u00e6ftigelsesindsats, skal kommunen neds\u00e6tte\nuddannelses- og kontanthj\u00e6lpen. Neds\u00e6ttelsen sker for Klagevejledning\ndet antal dage, hvor du helt eller delvist udebliver.\nDu kan klage over jobcenterets og kommunens afg\u00f8relser\nvedr\u00f8rende tilbuddet og ydelser.\nHvis du en gang afviser eller gentagne gange udebliver fra\net tilbud uden rimelig grund, oph\u00f8rer uddannelses- og kon- Du har mulighed for at klage over tilbuddet inden 4 uger fra\ntanthj\u00e6lpen, indtil du igen m\u00f8der i tilbuddet.\nmodtagelsen af tilbuddet. Jobcenteret skal have modtaget\nklagen inden fristen p\u00e5 4 uger. Hvis jobcenteret ikke giver\nHvis du undlader at melde sygdom neds\u00e6ttes hj\u00e6lpen.\ndig medhold i klagen, sendes den videre til Ankestyrelsen.\nErstatningsforhold\nUnder tilbudsforl\u00f8bet yder jobcenteret erstatning efter reglerne i lov om sikring mod f\u00f8lger af arbejdsskade, jf. besk\u00e6ftigelseslovens \u00a7 113. Jobcenteret yder ligeledes erstatning\nfor skader tilbudsmodtageren forvolder p\u00e5 andre personer\nFor at modtage befordringsgodtg\u00f8relse skal du udfylde en eller andres ejendele efter dansk rets almindelige regler, jf.\nselvst\u00e6ndig blanket, som enten udleveres af kommunen bek. om en aktiv besk\u00e6ftigelsesindsats, kapitel 12. Heraf\nf\u00f8lger, at der normalt ikke ydes erstatning, hvis en skade er\neller findes p\u00e5 kommunens hjemmeside.\nd\u00e6kket af en arbejdsskadeforsikring, en tingsforsikring eller\nen driftstabsforsikring.\nRet og pligt til tilbud\nModtagere af uddannelses- og kontanthj\u00e6lp har pligt til at\nS\u00e6rligt ved virksomhedspraktik\/nytteindsats\ntage imod tilbud fra jobcenteret.\nEn virksomhedspraktik\/nyttejob er ikke et ans\u00e6ttelsesforDu kan kun modtage tilbuddet s\u00e5 l\u00e6nge du er berettiget til hold, og tilbudsmodtageren\/praktikanten er derfor ikke omuddannelses- eller kontanth\u00e6lp. Retten til tilbuddet bortfal- fattet af de for l\u00f8nmodtagere g\u00e6ldende regler fastsat ved\nder fx hvis du eller din \u00e6gtef\u00e6lle opn\u00e5r indt\u00e6gter, som lov eller i henhold til lov eller ved kollektiv overenskomst m.v.\noverstiger eller svarer til din uddannelses- eller kontant- Dog er tilbudsmodtageren\/praktikanten omfattet af arbejdsmilj\u00f8lovgivningen og lov om forbud mod forskelsbehandling\nhj\u00e6lp.\np\u00e5 arbejdsmarkedet, jf. besk\u00e6ftigelseslovens \u00a7 43.\nTilbud fra jobcenteret kan kun modtages, s\u00e5 l\u00e6nge du bor i\nkommunen, medmindre andet aftales.\nBefordringsgodtg\u00f8relse\nDu kan ved deltagelse i tilbud ydes befordringsgodtg\u00f8relse\nved daglig transport over 24 km efter besk\u00e6ftigelseslovens\n\u00a7 82.\n\nKLE 15.20.00G01 AB 105 (05\/2018)\nUdarbejdet af KL\n\nSide 1 af 2\n\n\fJobcenterets registrering\nog videregivelse af oplysninger\nJobcenteret registrerer de modtagne oplysninger og videregiver oplysningerne til andre offentlige myndigheder, private\nvirksomheder m.fl., der har lovm\u00e6ssigt krav p\u00e5 oplysningerne eller samarbejder med Jobcenteret\/kommunen.\nJobcenteret sletter oplysningerne n\u00e5r opbevaringspligten\nudl\u00f8ber og et eventuelt arkiveringskrav er opfyldt. N\u00e5r oplysningerne er arkiveret eller slettet, har Jobcenteret ikke\nl\u00e6ngere adgang til dem.\nDu har ret til at vide, hvilke oplysninger Jobcenteret har\nom dig, og du kan kr\u00e6ve forkerte oplysninger rettet eller\nslettet.\n\nKommunens databeskyttelsesr\u00e5dgiver\nDu kan kontakte databeskyttelsesr\u00e5dgiveren om dine rettigheder i henhold til databeskyttelseslovgivningen.\nDu har ret til at klage til Datatilsynet over Jobcenterets\/\nkommunens behandling af dine personlige oplysninger.\nP\u00e5 Datatilsynet.dk kan du l\u00e6se mere om databeskyttelsesr\u00e5dgiverens rolle.\n\nKLE 15.20.00G01 AB 105 (05\/2018)\nUdarbejdet af KL\n\nSide 2 af 2\n\n\f"}