{"classes":[{"id":"15.17.06","title":""}],"title":"","text":"Forbeholdt kommunen\n\n5 708410 043598\n\nSendes til kommunen\n\nModtaget dato\n\ndp 300A\nOplysningsskema\nSygemeldt l\u00f8nmodtager\nLov om sygedagpenge, \u00a7 11, stk. 2\n\nNavn mv.\nNavn\n\nPersonnummer\n\nStilling\n\nUddannelse\n\n1. Oplysninger om frav\u00e6ret\nDato\n\nF\u00f8rste sygefrav\u00e6rsdag\nBeskriv kort, hvad du fejler\n\nHvis ja, hvorn\u00e5r\n\nHar du tidligere v\u00e6ret sygemeldt af samme \u00e5rsag\nNej\nJa\nJa\nJa\nNej\nHvis ja, \u00f8nsker du at benytte standby-ordningen\nEr der tale om en\nNej\nHvis\ndu\nhar\nen\nalvorlig\nlivstruende\nsygdom,\nbeh\u00f8ver\ndu\nikke\nat\ndeltage\ni\nkommunens\nlivstruende sygdom\nVed ikke opf\u00f8lgning. Det kaldes, at opf\u00f8lgningen s\u00e6ttes p\u00e5 standby.\n\n2. Tilbage i arbejde\nDato for sidste sygefrav\u00e6rsdag\n\nJeg er raskmeldt, og sidste sygefrav\u00e6rsdag var den\nJeg forventer at raskmelde mig fuldt ud inden for 8 uger\nefter f\u00f8rste sygefrav\u00e6rsdag\nHvorn\u00e5r forventer du at\nraskmelde dig\n\nForventet dato for sidste sygefrav\u00e6rsdag\nDato for delvis genoptagelse\n\nJeg har genoptaget arbejdet delvist\nJeg har ikke allerede genoptaget arbejdet delvist, men\nforventer at genoptage arbejdet delvist\n\nForventet dato for delvis genoptagelse\n\nJeg forventer ikke at raskmelde mig fuldt ud eller genoptage\narbejdet delvist inden for 8 uger efter f\u00f8rste sygefrav\u00e6rsdag\nHvis du er raskmeldt eller forventer at raskmelde dig helt inden for 8 uger efter f\u00f8rste sygefrav\u00e6rsdag, skal du udfylde\npunkt 5, 6 og 9 og returnere skemaet til kommunen.\nHvis du kun forventer at genoptage arbejdet delvist inden for 8 uger, eller slet ikke forventer at raskmelde dig inden for 8\nuger, skal du besvare samtlige punkter i skemaet.\nHvis du og din arbejdsgiver har lagt en plan for delvis genoptagelse af arbejdet, bedes du (hvis muligt) tage planen med\ntil din f\u00f8rste samtale i jobcenteret.\nJeg forventer at vende tilbage til min nuv\u00e6rende arbejdsplads\nTilbagevenden til\nPr. dato\nJeg er blevet opsagt\nmin nuv\u00e6rende\nJeg\nhar\nselv\nsagt\nop\narbejdsplads\nAf anden \u00e5rsag vender jeg ikke tilbage\n\u00c5rsag\n\nKLE 15.17.06G01 DP 300A (05\/2018)\nUdarbejdet af KL\n\nSide 1 af 4\n\n\fPersonnummer\n\nNavn\n\n3. Behandling\nEr du i behandling\n\nNej\n\nAfventer behandling\/\nunders\u00f8gelse\n\nJa\n\nForventet dato\n\nHvis behandlingen ikke foreg\u00e5r hos egen l\u00e6ge, oplys da navn og adresse p\u00e5 l\u00e6ge\/sygehus (Dette oplyses ogs\u00e5, hvis du er i sygesikringsgruppe 2)\n\n4. Oplysninger om arbejdsplads og arbejdsfunktioner\nDato\n\nHvorn\u00e5r blev du ansat p\u00e5 din nuv\u00e6rende arbejdsplads\nHvis ja, hvor l\u00e6nge\nJa\nHar din sygdom p\u00e5virket dit arNej\nbejde, inden du blev sygemeldt\nHar du f\u00e5et udarbejdet en fastholdelsesplan\n\nJa\n\nNej, men planlagt\n\nNej\n\nHar du f\u00e5et udarbejdet en mulighedserkl\u00e6ring\n(l\u00e6geerkl\u00e6ring til din arbejdsgiver)\nJa\nNej, men planlagt\nNej\nTil brug for den konsultation, du skal have med din l\u00e6ge, skal du svare p\u00e5 f\u00f8lgende tre sp\u00f8rgsm\u00e5l. Nedenfor kan du se,\nhvad din arbejdsgiver har svaret.\nDine svar\n\nHvilke af dine arbejdsopgaver\/arbejdsfunktioner er\np\u00e5virket af sygdommen\n\nArbejdsgivers svar\n\nDine svar\n\nHvor l\u00e6nge har sygdommen p\u00e5virket dit arbejde\n\nArbejdsgivers svar\n\nDine svar\n\nEr arbejdet fors\u00f8gt tilpasset\ndin tilstand\n\nArbejdsgivers svar\n\n5. Arbejdsskade\nSkyldes dit sygefrav\u00e6r en arbejdsskade\n\nNej\n\nJa\n\nHvis ja, er arbejdsskaden anmeldt til Arbejdsskadestyrelsen\n\nNej\n\nJa\n\n6. Sygdom\/personskade\nSkyldes dit sygefrav\u00e6r\n\nsygdom\n\npersonskade\n\nHvis personskade, skriv kort hvordan skaden skete\n\nHvis personskade, oplys navn og adresse p\u00e5 skadevolderens\/modpartens forsikringsselskab\nSkadenummer\n\nPolicenummer\n\nKLE 15.17.06G01 DP 300A (05\/2018)\nUdarbejdet af KL\n\nSide 2 af 4\n\n\fPersonnummer\n\nNavn\n\n7. Kontaktperson\nOplys gerne en kontaktperson hos din arbejdsgiver, som vi kan kontakte i forbindelse med dit opf\u00f8lgningsforl\u00f8b i jobcenteret\nNavn\n\nTelefonnummer\n\nE-mail\n\n8. Fuldmagt\nDa jeg er for syg til selv at varetage min sag, giver jeg hermed fuldmagt til nedenst\u00e5ende\nNavn\nAdresse\n\nTelefonnummer\n\nE-mail\n\n9. Samtykkeerkl\u00e6ring og underskrift\nJeg giver hermed samtykke til, at kommunen kan indhente l\u00e6geerkl\u00e6ring eller andre helbredsoplysninger om mig.\nOplysningerne kan indhentes fra min l\u00e6ge, speciall\u00e6ge eller hospital, som er oplyst i punkt 3. Kommunen indhenter\nkun de oplysninger, der er n\u00f8dvendige for at behandle din sag om sygedagpenge. Kommunen pr\u00e6ciserer overfor\ndin l\u00e6ge, speciall\u00e6ge eller hospital, hvilke oplysninger kommunen har brug for.\nJeg \u00f8nsker ikke at give kommunen mit samtykke til at indhente helbredsoplysninger om mig. Jeg er indforst\u00e5et med,\nat opf\u00f8lgningen dermed behandles p\u00e5 basis af de her foreliggende oplysninger. Hvis du ikke giver samtykke, kan det\nf\u00e5 konsekvenser for dine sygedagpenge.\nJa\nNej\n\nJeg giver hermed mit samtykke til at kommunen unders\u00f8ger, om der i Udbetaling Danmark er oprettet\nen kontrolsag vedr\u00f8rende andre kontante ydelser eller \u00f8konomiske tilskud, som jeg modtager og hvad\nkontrolsagen i s\u00e5 fald drejer sig om.\n\nHvis du har ans\u00f8gt om sygedagpenge fra kommunen, kan kommunen inden en evt. bevilling af sygedagpenge f\u00e5 brug\nfor at unders\u00f8ge, om der er oprettet en kontrolsag p\u00e5 andre kontante ydelser, som du modtager fra det offentlige, jf. lov\nom Udbetaling Danmark \u00a7 11a. En kontrolsag oprettes, hvis der er mistanke om socialt bedrageri. Er der oprettet en\ns\u00e5dan kontrolsag, kan det have konsekvenser for, om du er berettiget til sygedagpenge.\nN\u00e5r f\u00f8rst du er bevilliget sygedagpenge kan kommunen uden dit samtykke f\u00e5 adgang til n\u00f8dvendige oplysninger i\nUdbetaling Danmark omkring kontrolsager p\u00e5 andre ydelser. Adgangen omfatter, at vi kan se hvad der unders\u00f8ges,\nhvilke skridt, der er taget i sagen og om der er blevet lukket en kontrolsag om dig inden for de seneste 6 m\u00e5neder.\nTilsvarende videregiver vi samme oplysninger til Udbetaling Danmark, jf. Lov om Udbetaling Danmark \u00a7 11b.\nDu skal besvare sp\u00f8rgsm\u00e5lene p\u00e5 oplysningsskemaet til\nbrug for kommunens opf\u00f8lgning af udbetaling af sygedagpenge, jf. sygedagpengelovens \u00a7 11, stk. 2.\nN\u00e5r du modtager ydelser fra kommunen, har du pligt til at\noplyse om \u00e6ndringer, der kan have betydning for sagen, jf.\nRetssikkerhedslovens \u00a7 11, stk. 2. Oplysninger med betydning for sagen kan v\u00e6re p\u00e5begyndelse af arbejde eller uddannelse, at du tager p\u00e5 ferie eller ophold i udlandet under\nsygdommen, forv\u00e6rring af din sygdom eller \u00e6ndringer\nmht. behandling mv. Som udgangspunkt er sygdom en feriehindring og der kan ikke udbetales sygedagpenge under\nferie. Du skal altid kontakte din kommune, hvis du \u00f8nsker\nat holde ferie. Eventuel ferie m\u00e5 ikke forhale udredning,\nbehandling, optrapning i tid, afklaring m.v.\nForkerte eller manglende oplysninger kan medf\u00f8re, at\nder rejses krav om tilbagebetaling af ydelsen, jf. sygedagpengelovens \u00a7 71, stk. 2.\nHvis du giver forkerte, mangelfulde eller vildledende oplysninger \u2013 enten bevidst eller ved grov uagtsomhed \u2013 kan\ndu blive id\u00f8mt b\u00f8de efter retssikkerhedslovens \u00a7 12b eller\ntiltales efter straffelovens \u00a7 289a.\nOm samtykke\nReglerne om samtykke fremg\u00e5r af databeskyttelsesforordningen.\n\nVed samtykke forst\u00e5s \u201denhver frivillig, specifik, informeret og utvetydig viljestilkendegivelse fra den registrerede,\nhvorved den registrerede ved erkl\u00e6ring eller klar bekr\u00e6ftelse indvilliger i, at personoplysninger, der vedr\u00f8rer den\np\u00e5g\u00e6ldende, g\u00f8res til genstand for behandling.\u201d Jf. persondataforordningen artikel 4 nr. 11.\nDu kan altid tilbagekalde et samtykke til indhentning eller\nvideregivelse af oplysninger, jf. databeskyttelsesforordningens artikel 7, stk. 3.\nDit samtykke bortfalder automatisk n\u00e5r sagen er f\u00e6rdigbehandlet.\nOplysninger kommunen\nkan indhente uden dit samtykke\nKommunen kan indhente \u00f8konomiske oplysninger samt\noplysninger om dine ferieforhold fra\n\u2022\nandre offentlige myndigheder,\n\u2022\neIndkomstregistret,\n\u2022\nA-kasser og\n\u2022\nFeriekonto.\nKommunen kan indhente tilsvarende oplysninger om andre i din husstand. Kommunen bruger oplysningerne til behandling af din sag eller til efterf\u00f8lgende kontrol, jf. retssikkerhedslovens \u00a7 11a, stk. 2 til 5.\n\nKLE 15.17.06G01 DP 300A (05\/2018)\nUdarbejdet af KL\n\nSide 3 af 4\n\n\fNavn\n\nKommunen kan til kontrolform\u00e5l indhente n\u00f8dvendige oplysninger fra\n\u2022\narbejdsgivere om l\u00f8n- og besk\u00e6ftigelsesperioder m.v.\n\u2022\npensionskasser, livsforsikringsselskaber og pengeinstitutter om pensionsforhold m.v.\njf. lov om organisering og underst\u00f8ttelse af besk\u00e6ftigelsesindsatsen m.v., \u00a7 54, stk. 2.\nKommunen kan via Udbetaling Danmark samk\u00f8re n\u00f8dvendige ikkef\u00f8lsomme personoplysninger fra andre offentlige myndigheder, udenlandske myndigheder og arbejdsl\u00f8shedskasser til brug for kontrol i forbindelse med\nans\u00f8gning om og udbetaling af ydelser. Samk\u00f8ring kan\nske med data fra egne registre. Resultatet af samk\u00f8ring\nkan i visse tilf\u00e6lde samk\u00f8res med oplysninger fra andre\nvirksomheder \u2013 fx Post Nord, jf. Lov om Udbetaling Danmark \u00a7 12a.\nKommunen kan ogs\u00e5 kr\u00e6ve andre n\u00f8dvendige oplysninger fra\n\u2022\nandre offentlige myndigheder,\n\u2022\nATP,\n\u2022\nNemKonto, og\n\u2022\nA-kasser.\nOplysningerne kan samk\u00f8res og sammenholdes med\ndata i andre it-systemer, der tilh\u00f8rer kommunen, andre\nmyndigheder eller A-kasser, jf. lov om organisering og underst\u00f8ttelse af besk\u00e6ftigelsesindsatsen m.v., \u00a7 54, stk. 3.\nKommunen kan udveksle oplysninger med Arbejdsmarkedets Erhvervssikring om din sag, jf. retssikkerhedslovens \u00a7 12d.\nDato og underskrift\n\nPersonnummer\n\nKommunen har adgang til at foretage kontrolbes\u00f8g p\u00e5\nden virksomhed, hvor du er eller har v\u00e6ret ansat for at\nkontrollere de l\u00f8nudbetalinger, som danner grundlag for\nberegningen af sygedagpenge. Ved bes\u00f8get har kommunen ret til at udsp\u00f8rge dig og de \u00f8vrige ansatte iht. retssikkerhedslovens \u00a7 12a.\nKommunens registrering\nog videregivelse af oplysninger\nKommunen registrerer de modtagne oplysninger og videregiver oplysningerne til andre offentlige myndigheder, private virksomheder m.fl., der har lovm\u00e6ssigt krav p\u00e5 oplysningerne eller samarbejder med kommunen.\nKommunen sletter oplysningerne n\u00e5r opbevaringspligten udl\u00f8ber og et eventuelt arkiveringskrav er opfyldt. N\u00e5r\noplysningerne er arkiveret eller slettet, har kommunen\nikke l\u00e6ngere adgang til dem.\nDu har ret til at vide, hvilke oplysninger kommunen har\nom dig, og du kan kr\u00e6ve forkerte oplysninger rettet eller\nslettet.\nKommunens databeskyttelsesr\u00e5dgiver\nDu kan kontakte databeskyttelsesr\u00e5dgiveren om dine rettigheder i henhold til databeskyttelseslovgivningen.\nDu har ret til at klage til Datatilsynet over Kommunens\nbehandling af dine personlige oplysninger.\nP\u00e5 Datatilsynet.dk kan du l\u00e6se mere om databeskyttelsesr\u00e5dgiverens rolle.\nTelefonnummer i dagtimerne\n\nKLE 15.17.06G01 DP 300A (05\/2018)\nUdarbejdet af KL\n\nSide 4 af 4\n\n\f"}