{"classes":[{"id":"32.39.00","title":""}],"title":"","text":"DEN ADMINISTRATIVE KOMMISSION FOR\nVANDRENDE ARBEJDSTAGERES\nSOCIALE SIKRING\n\nBenyttes fra 1. maj 2010 ogs\u00e5 med hjemmel i de tilsvarende artikler\ni Forordning (EF) nr. 883\/2004 og Forordning (EF) nr. 987\/2009\n\nE 107\n\nDK\n\n(1 )\n\nTo be used after 1 May 2010 under the equivalent provisions in\nRegulation (EC) 883\/2004 and Regulation (EC) 987\/2009\n\nANS\u00d8GNING OM ATTEST FOR RET TIL NATURALYDELSER\nForordning (E\u00d8F) nr. 1408\/71: art. 19.1.a; art. 19.2; art. 22.1.a.i, b.i og c.i; art. 22.3; art. 25.1.a og 3.i; art. 26.1; art. 28.1.a;\nart. 29.1.a; art. 31.a; art. 52.a; art. 55.1.a.i, b.i og c.i\nForordning (E\u00d8F) nr. 574\/72: art. 17.1; art. 21.1; art. 22.1 og 3; art. 23; art. 27, f\u00f8rste punktum; art. 28; art. 29.1 og 2; art. 30.1; art. 31.1 og 3;\nart. 60.1; art. 62.3, 4 og 7; art. 63.1 og 3\nAfsnit A udfyldes af bop\u00e6ls- eller opholdsstedets institution, som sender to eksemplarer af blanketten til den kompetente institution under\niagttagelse af bestemmelserne i de anf\u00f8rte artikler i forordning (E\u00d8F) nr. 574\/72. Hvis den kompetente institution ikke mener at kunne fremsende\nden \u00f8nskede blanket, udfylder den afsnit B og sender det ene af de to eksemplarer tilbage til den institution, hvorfra den har modtaget blanketten.\nHvis det kompetente land er Belgien, skal blanketten sendes til sygeforsikringsinstitutionen, undtagen i de tilf\u00e6lde, hvor det drejer sig om en p\u00e5vist\narbejdsulykke eller en anerkendt erhvervssygdom.\nBlanketten skal udfyldes med blokbogstaver, og der m\u00e5 kun skrives p\u00e5 de punkterede linjer. Den best\u00e5r\naf 4 sider, hvoraf ingen m\u00e5 fjernes.\n\nA. Udfyldes af bop\u00e6ls- eller opholdsstedets institution\n1.\n\nDen institution, som blanketten sendes til\n\n1.1\n1.2\n\nBetegnelse: ...............................................................................................................................................................................................\nInstitutionens identi\ufb01kationsnummer: .......................................................................................................................................................\n\n1.3\n\nAdresse: ....................................................................................................................................................................................................\n...................................................................................................................................................................................................................\n\n2.\n\n\u25a1 Den forsikrede\n\n2.1\n\nEfternavn (2):\n\n2.2\n\nFornavne (3):\n\nF\u00f8dselsdato:\n\n......................................................................................................\n\n......................................................................................................\n\n...................................................................................................................................................................................................................\n\n2.3\n\nTidligere navne: ........................................................................................................................................................................................\n\n2.4\n\nAdresse: ...................................................................................................................................................................................................\n...................................................................................................................................................................................................................\n\n2.5\n2.6\n\nPersonnummer (4):\n...................................................................................................................................................................................................................\n\n\u25a1 Modtager af\n\n\u25a1 Ans\u00f8ger om\n\npension i anledning af\n\n\u25a1 alderdom\n\u25a1 arbejdsulykke\n2.7\n\n\u25a1 invaliditet\n\u25a1 erhvervssygdom\n\n\u25a1 d\u00f8dsfald\n\nDen institution, som det p\u00e5hviler at udbetale pension:\n...................................................................................................................................................................................................................\n\n3.\n\n\u25a1 Seneste arbejdsgiver ( )\n\n3.1\n\nNavn eller \ufb01rmanavn: ...............................................................................................................................................................................\n\n3.2\n\n5\n\n\u25a1 Seneste selvst\u00e6ndige virksomhed ( )\n5\n\nAdresse: ...................................................................................................................................................................................................\n...................................................................................................................................................................................................................\n\n3.3\n\nErhvervsgren (6): .......................................................................................................................................................................................\n\n3.4\n\nDen ulykkesforsikringsinstitution, som arbejdsgiveren er tilsluttet (7): ......................................................................................................\n...................................................................................................................................................................................................................\n...................................................................................................................................................................................................................\n...................................................................................................................................................................................................................\n\n1\n\nKLE 32.39.00G01 E 107 (05\/2010)\nUdarbejdet af EU\n\nKommuneinformation\nSide 1 af 4\n\n\fE 107\nDK\n4.\n\nFamiliemedlemmer (8)\n\n4.1\n\nEfternavn (2)\n\nFornavne (3)\n\nF\u00f8dselsdato\n\nPersonnummer (4)\n\n.........................................................\n\n..............................................\n\n...................................\n\n...............................................\n\n.........................................................\n\n..............................................\n\n.....................................\n\n...............................................\n\n.........................................................\n\n..............................................\n\n.....................................\n\n...............................................\n\n.........................................................\n\n..............................................\n\n.....................................\n\n...............................................\n\n.........................................................\n\n..............................................\n\n.....................................\n\n...............................................\n\n.........................................................\n\n..............................................\n\n.....................................\n\n...............................................\n\n.........................................................\n\n..............................................\n\n.....................................\n\n...............................................\n\n......................................................... \u2026\u2026\u2026\u2026\u2026\u2026\u2026\u2026\u2026\u2026\u2026\u2026\u2026\n\n.....................................\n\n...............................................\n\n4.2\n\nAdresse i bop\u00e6lslandet (9): \u2026\u2026\u2026.\u2026\u2026\u2026\u2026\u2026\u2026\u2026\u2026\u2026\u2026\u2026\u2026\u2026\u2026\u2026\u2026\u2026\u2026\u2026\u2026\u2026\u2026\u2026\u2026.\u2026\u2026\u2026\u2026\u2026\u2026\u2026\u2026\u2026\u2026\u2026......................\n\u2026\u2026\u2026\u2026\u2026\u2026\u2026\u2026\u2026\u2026\u2026\u2026\u2026\u2026\u2026\u2026\u2026\u2026\u2026\u2026\u2026\u2026\u2026\u2026\u2026\u2026\u2026\u2026\u2026\u2026\u2026\u2026\u2026\u2026\u2026\u2026\u2026\u2026\u2026\u2026\u2026\u2026\u2026\u2026\u2026\u2026\u2026\u2026\u2026\u2026\u2026\u2026\u2026\u2026\u2026......\n\n5.\n\nVi har den ................................................................... modtaget en ans\u00f8gning fra den i\n\n\u25a1 punkt 2\n\n\u25a1 punkt 4\n\nanf\u00f8rte person om\n5.1\n5.2\n5.3\n6.\n6.1\n6.2\n\n\u25a1 tilkendelse af naturalydelser\n\u25a1 bevarelse af ret til naturalydelser\n\u25a1 registrering her som v\u00e6rende berettiget til naturalydelser\n\u25a1 er bevilget\nNaturalydelserne\ni henhold til artikel\n\u25a1 29.2\n\u25a1 60.1\nAns\u00f8geren\n\u25a1 har indtil dags dato ikke haft arbejde\n\u25a1 har ud\u00f8vet f\u00f8lgende besk\u00e6ftigelse:\n\n\u25a1 er ikke bevilget\n\u25a1 62.3 i forordning (E\u00d8F) nr. 574\/72.\n\n..........................................................................................................................................................\n\n7.\n\nDe bedes sende en attest for ret til naturalydelser i form af\n\n\u25a1 blanket E .....................................................................................................................................................................................\n\u25a1 et sygesikringsbevis, der midlertidigt erstatter det europ\u00e6iske sygesikringskort, eller et europ\u00e6isk sygesikringskort (hvis dette kort\nkan udstedes i henhold til den kompetente stats lovgivning),\n\nder er gyldig fra .................................................... til ......................................................................................................................\n8.\n\n\u25a1 L\u00e6geerkl\u00e6ring vedl\u00e6gges (\n\n10\n\n)\n\n9.\n\nBop\u00e6ls- eller opholdsstedets institution\n\n9.1\n\nBetegnelse: ...............................................................................................................................................................................................\n\n9.2\n\nInstitutionens identi\ufb01kationsnummer: .......................................................................................................................................................\n\n9.3\n\nAdresse: ....................................................................................................................................................................................................\n\n9.4\n\nStempel\n\n..................................................................................................................................................................................................................\n9.5\n\nDato: ..............................................................................\n\n9.6\n\nUnderskrift:\n.......................................................................................\n\n2\n\nKLE 32.39.00G01 E 107 (05\/2010)\nUdarbejdet af EU\n\nKommuneinformation\nSide 2 af 4\n\n\fE 107\nB. Udfyldes af den kompetente institution\n\nDK\n10.\n10.1\n10.2\n\n\u25a1 De bedes sende et udfyldt og underskrevet eksemplar af vedlagte attest tilbage. (\n\u25a1 Vi er ikke i stand til at udstede den i afsnit A \u00f8nskede attest, fordi\n\n11\n\n)\n\n....................................................................................................................................................................................................................\n....................................................................................................................................................................................................................\n11.\n\nDen kompetente institution\n\n11.1\n\nBetegnelse: .................................................................................................................................................................................................\n\n11.2\n\nInstitutionens identi\ufb01kationsnummer: .........................................................................................................................................................\n\n11.3\n\nAdresse: .....................................................................................................................................................................................................\n....................................................................................................................................................................................................................\n....................................................................................................................................................................................................................\n\n11.4\n\nStempel\n\n11.5\n\nDato:\n.........................................................................................\n\n11.6\n\nUnderskrift:\n.........................................................................................\n\n3\n\nKLE 32.39.00G01 E 107 (05\/2010)\nUdarbejdet af EU\n\nKommuneinformation\nSide 3 af 4\n\n\fE 107\nFODNOTER\n\nDK\n(1 )\n\nKendingsbogstaver for det land, hvor blanketten udfyldes: BE = Belgien; CZ = Tjekkiet; DK = Danmark; DE = Tyskland; EE = Estland;\nGR = Gr\u00e6kenland; ES = Spanien; FR = Frankrig; IE = Irland; IT = Italien; CY = Cypern; LV = Letland; LT = Litauen; LU = Luxembourg;\nHU = Ungarn; MT = Malta; NL = Nederlandene; AT = \u00d8strig; PL = Polen; PT = Portugal; SI = Slovenien; SK = Slovakiet; FI = Finland;\nSE = Sverige; UK = Det Forenede Kongerige; IS = Island; LI = Liechtenstein; NO = Norge; CH = Schweiz.\n\n(2 )\n\nAnf\u00f8r alle efternavne i samme r\u00e6kkef\u00f8lge som p\u00e5 d\u00e5bsattesten.\n\n(3 )\n\nAnf\u00f8r alle fornavne i samme r\u00e6kkef\u00f8lge som p\u00e5 d\u00e5bsattesten.\nTil brug for institutioner i Italien anf\u00f8res skattenummer (codice \ufb01scale).\n\n(4 )\n\nHvis blanketten er bestemt for en maltesisk institution, anf\u00f8res for maltesiske statsborgere nummeret p\u00e5 identitetskortet, eller for personer,\nder ikke er maltesiske statsborgere, det maltesiske socialsikringsnummer.\nTil brug for institutioner i Slovakiet anf\u00f8res i givet fald det slovakiske f\u00f8dselsnummer.\nHvis blanketten er bestemt for en spansk institution, anf\u00f8res i givet fald for spanske statsborgere nummeret p\u00e5 det spanske identitetskort\n(D.N.I.) eller for udl\u00e6ndinges vedkommende N.I.E. Hvis kortet er udl\u00f8bet, anf\u00f8res i begge tilf\u00e6lde \u00bbintet\u00ab.\n(5 )\n\nSkal kun udfyldes, n\u00e5r blanketten vedr\u00f8rer en arbejdstager, en selvst\u00e6ndig erhvervsdrivende eller en arbejdsl\u00f8s.\n\n(6 )\n\nSkal kun udfyldes, n\u00e5r blanketten vedr\u00f8rer en arbejdstager, der anses for at have v\u00e6ret offer for en arbejdsulykke.\n\n7\n\n()\n\nI Spanien: \u00bbDirecci\u00f3n Provincial del Instituto Nacional de la Seguridad Social\u00ab (provinsafdelingen af statsanstalten for social sikring) eller\n\u00bbDirecci\u00f3n Provincial del Instituto Social de la Marina\u00ab (provinsafdelingen af socialinstituttet for s\u00f8farende), for s\u00e5 vidt ang\u00e5r s\u00e6rordningen\nfor s\u00f8farende.\n\n(8 )\n\nSkal kun udfyldes for familiemedlemmer, for hvem der er indgivet ans\u00f8gning om ydelser eller registrering. N\u00e5r det drejer sig om registrering,\nskal der kun anf\u00f8res \u00e9t familiemedlem.\n\n(9)\n\nSkal kun udfyldes, hvis familiemedlemmets adresse er en anden end familiefors\u00f8rgerens.\n\n(10)\n\nSkal kun vedl\u00e6gges, hvis det er n\u00f8dvendigt. I s\u00e5 fald s\u00e6ttes der kryds i den p\u00e5g\u00e6ldende boks.\n\n(11)\n\nTil brug for institutioner I Nederlandene og Schweiz og s\u00e5fremt arten af den blanket, der skal fremsendes, g\u00f8r det muligt.\n\n4\n\nKLE 32.39.00G01 E 107 (05\/2010)\nUdarbejdet af EU\n\nKommuneinformation\nSide 4 af 4\n\n\f"}