{"classes":[{"id":"54.15.28","title":""}],"title":"","text":"5 708410 039874\n\nPr\u00f8veafholders navn, adresse, telefonnr., inst.kode\n\nPr\u00f8veprotokol\nMedborgerskabspr\u00f8ven\n\nPr\u00f8vedeltager\nNavn\n\nMedborgerskabspr\u00f8ve\n1.\n\nPersonnummer\n\nAntal rigtigt\nbesvarede\nsp\u00f8rgsm\u00e5l\n\nBest\u00e5et\nM\u00e5ned\/\u00e5r\n\nIkke\nbest\u00e5et\nM\u00e5ned\/\u00e5r\n\nBem\u00e6rkninger\n\n2.\n\n3.\n\n4.\n\n5.\n\n6.\n\nLeder\nDato og underskrift\n\nDato og underskrift\n\nDato og underskrift\n\nDato og underskrift\n\nDato og underskrift\n\nDato og underskrift\n\nKLE 54.15.28G01 IN 990 (04\/2017)\nUdarbejdet af Udl\u00e6ndinge- og Integrationsministeriet og godkendt af KL\n\nSide 1 af 1\n\n\f"}