{"classes":[{"id":"32.03.16","title":""}],"title":"","text":"Sendes til kommunen\n\nUdfyldes af kommunen\nModtaget dato\n\nKLE 32.03.16 G01 \u2022 Sagsidentifikation\n\nOplysninger til brug for opstart\naf f\u00f8rtidspension\nefter pensionslovens kapitel 3\nDu er blevet tilkendt f\u00f8rtidspension. Til beregning af din f\u00f8rtidspension skal vi bruge oplysninger om\ndine samlivs- og indkomstforhold samt andre oplysninger til brug ved udbetalingen.\nNavn\nNavn\n\nPersonnummer\n\nSamlivsforhold\nEnlig\n\nSamlevende med\n\u00e6gtef\u00e6lle\n\nSamlevende\nmed anden person\n\nSamboende med sl\u00e6gtning, som\njeg ikke kan indg\u00e5 \u00e6gteskab med\n\n\u00c6gtef\u00e6lles\/samlevers navn\n\nPersonnummer\n\nSkattekort\nAnvend hovedkort\nAnvend bikort\nDu skal sikre dig, at dit hovedkort ikke anvendes flere steder p\u00e5 samme tid.\n\nAnvend frikort\n\nPensionen vil blive indsat p\u00e5 din NemKonto.\n\nForventet personlig indkomst efter overgang til f\u00f8rtidspension \u2013 f\u00f8r skat\nDig selv\nL\u00f8nindkomst og honorarer fratrukket arbejdsmarkedsbidrag og ATP-bidrag\n\nKr. pr. m\u00e5ned\n\n\u00c6gtef\u00e6lle\/samlever\nKr. pr. \u00e5r\n\nKr. pr. m\u00e5ned\n\nKr. pr. \u00e5r\n\nOverskud af selvst\u00e6ndig virksomhed fratrukket arbejdsmarkedsbidrag og kapitalafkast\nUnderskud af selvst\u00e6ndig virksomhed\nPensioner\n\nPension fra ATP\nTjenestemandspension\nUdenlandsk pension\nUdbetaling fra indekskontrakter, rateforsikring og lign.\n\u2013 angiv art\nAnden pension \u2013 angiv art\n\nDelpension\nDagpenge\n\nEfterl\u00f8n\n\nOvergangsydelse\n\nSkattepligtig kontanthj\u00e6lp\nAndre indkomster \u2013 angiv art fx DIS-indkomst\n\nAndre\npersonlige\nindkomster\nFradrag for pr\u00e6mier og bidrag til pensionsordninger mv.,\nsom ikke er fratrukket i l\u00f8nnen\nSP 216 (05\/2011)\nUdarbejdet af KL\n\nKommuneinformation\nSide 1 af 5\n\n\fNavn\n\nPersonnummer\n\nKapital- og aktieindkomst (f\u00f8r udbytteskat)\nDig selv: Kr. pr. \u00e5r\n\n\u00c6gtef\u00e6lle\/samlever: Kr. pr. \u00e5r\n\nLejeindt\u00e6gter m.m.\nRenteindt\u00e6gter\n(og kapitalafkast efter virksomhedsskatteloven)\nAnden kapitalindkomst \u2013 angiv art\n\nRenteudgifter\nAktieindkomst, hvor der er indeholdt udbytteskat\nAnden aktieindkomst\n\nUdfyldes, hvis du og\/eller din \u00e6gtef\u00e6lle\/samlever driver selvst\u00e6ndig virksomhed\nDeltager du\/din \u00e6gtef\u00e6lle\/samlever\naktivt i driften\nEr du\/din \u00e6gtef\u00e6lle\/samlever med i enten virksomhedsordningen eller kapitalafkastordningen\n\nDig selv:\n\n\u00c6gtef\u00e6lle\/samlever:\n\nNej\n\nJa\n\nNej\n\nJa\n\nHvis ja:\n\nNej\n\nJa\n\nNej\n\nJa\n\nHvis ja:\n\nVirksomhedsordningen\nKapitalafkastordningen\n\nVirksomhedsordningen\nKapitalafkastordningen\n\nForudl\u00f8nnet\/bagudl\u00f8nnet\nModtager du inden overgang til f\u00f8rtidspension\nforudbetalt l\u00f8n\/offentlig fors\u00f8rgelsesydelse\n\nNej\n\nJa\n\nHvis ja, vedl\u00e6g dokumentation\n\nHvis du ved overgangen til f\u00f8rtidspension modtager forudbetalt l\u00f8n eller offentlig fors\u00f8rgelsesydelse, udbetales en ekstra\nm\u00e5neds pension forud. L\u00f8bende pensionsudbetalinger, som fx tjenestemandspension, giver ikke ret til en ekstra m\u00e5neds\npension.\n\nSamtykkeerkl\u00e6ring\nJeg giver hermed samtykke til, at kommunen videregiver oplysninger\nom min f\u00f8rtidspension til nedenst\u00e5ende\n\nJa\n\nNej\n\nHvis nej, skal du selv underrette de pensionsselskaber, hvor du har en pensionsordning.\n\u2022 PensionDanmark, som tidligere var B&A Pension,\nHTS Pension og PKS Pension\n\u2022 PKA - Pensionskassernes Administration A\/S,\nsom omfatter pensionskasserne for sygeplejersker, ergoterapeuter og fysioterapeuter, kost- og\nern\u00e6ringsfaglige, bioanalytikere, jordem\u00f8dre,\nkontorfunktion\u00e6rer, l\u00e6gesekret\u00e6rer og socialr\u00e5dgivere og socialp\u00e6dagoger\n\nVideregivelsen omfatter oplysning om\n\u2022 hvilken kommune, der har tilkendt f\u00f8rtidspensionen\n\u2022 mit personnummer\n\u2022 at der er tale om ny f\u00f8rtidspension\n\u2022 hvilken dato pensionssagen er p\u00e5begyndt, og hvilken dato pensionen er tilkendt\nOplysningerne bliver sendt elektronisk. Samtykket er\nkun g\u00e6ldende i 30 dage efter modtagelsen af samtykket eller efter tilkendelsen af f\u00f8rtidspensionen.\n\nSP 216 (05\/2011)\nUdarbejdet af KL\n\nKommuneinformation\nSide 2 af 5\n\n\fNavn\n\nPersonnummer\n\nTilmelding til Supplerende Arbejdsmarkedspension (se side 5)\nVil du tilmelde dig Supplerende Arbejdsmarkedspension\nATP (Arbejdsmarkedets Till\u00e6gspension)\nLivsforsikringsselskab eller pensionskasse\nUdfyldes i\nforbindelse\nmed valg af\nlivsforsikingsselskab eller\npensionskasse\n\nEksisterende pensionsordning\n\nJa\n\nNej\n\nTilmelding af selskab har virkning fra den 1. i m\u00e5neden,\nefter at der er g\u00e5et en m\u00e5ned, fra du har givet kommunen\nmeddelelse herom.\n\nNy pensionsordning\n\nLivsforsikringsselskabets\/pensionskassens navn\n\nAftale-\/forsikringsnummer\n\nAdresse\n\nUnderskrift\nDu bedes besvare alle relevante sp\u00f8rgsm\u00e5l, idet dette vil lette\nkommunens sagsbehandling, jf. retssikkerhedslovens \u00a7 11,\nstk. 1.\nEfter retssikkerhedslovens \u00a7 11, stk. 2, har du pligt til straks at\nunderrette pensionskontoret om enhver \u00e6ndring i dine og din\n\u00e6gtef\u00e6lles\/samlevers personlige og \u00f8konomiske forhold, som\nkan medf\u00f8re en \u00e6ndring af pensionen. Forkerte eller manglende oplysninger kan medf\u00f8re tilbagebetaling, jf. pensionslovens \u00a7 42.\nEndvidere kan du \u2013 hvis du ved grov uagtsomhed eller bevidst\nafgiver urigtige eller vildledende oplysninger \u2013 id\u00f8mmes b\u00f8de\nefter retssikkerhedslovens \u00a7 12b eller tiltales efter straffelovens \u00a7 289a.\nTil beregning og kontrol kan kommunen uden dit samtykke\nindhente oplysninger \u2013 bl.a. ved samk\u00f8ring af data \u2013 om\n\u00f8konomiske forhold fra andre offentlige myndigheder, herunder\nkommuner, og arbejdsl\u00f8shedskasser, jf. retssikkerhedslovens\n\u00a7 11a, stk. 2 og 4.\n\nindkomst og formue, jf. retssikkerhedslovens \u00a7 11a, stk. 3.\nOplysningerne kan sammenstilles med de \u00f8vrige oplysninger\nom dine \u00f8konomiske forhold, som kommunen er i besiddelse\naf.\nKommunen har endvidere adgang til en virksomheds lokaler og\narbejdssteder med henblik p\u00e5 at kontrollere de l\u00f8nudbetalinger,\nsom danner grundlag for din pension. Ved bes\u00f8get kan kommunen udsp\u00f8rge de ansatte om navn, adresse, f\u00f8dselsdato,\nans\u00e6ttelsesperiode, l\u00f8n- og ans\u00e6ttelsesforhold og hvilke\nsociale og besk\u00e6ftigelsesm\u00e6ssige ydelser, de modtager,\nog kommunen kan p\u00e5l\u00e6gge arbejdsgiveren at registrere de\nansattes arbejdstider mv., jf. retssikkerhedslovens \u00a7 12a.\nKommunen registrerer de modtagne oplysninger og videregiver oplysningerne til andre offentlige myndigheder, private\nvirksomheder m.fl., der har lovm\u00e6ssigt krav p\u00e5 oplysningerne\neller samarbejder med kommunen.\nDu har ret til at f\u00e5 at vide, hvilke oplysninger kommunen behandler om dig. Du kan kr\u00e6ve forkerte oplysninger rettet.\n\nKommunen kan ogs\u00e5 kr\u00e6ve n\u00f8dvendige oplysninger fra\npengeinstitutter og arbejdsgivere til stikpr\u00f8vekontrol om din\nDato og underskrift\n\nE-mail\n\nTelefonnummer\n\nForbeholdt livsforsikringsselskab\/pensionskasse\nHerved bekr\u00e6ftes, at der er oprettet en pensionsordning, som opfylder\nkravene til supplerende arbejdsmarkedspension efter lov om social\npension \u00a7\u00a7 33b-33e \u2013 dvs. en livsvarig pension, der udbetales fra folkepensionsalderen. Der kan ikke indbetales til kapital- og ratepensioner.\n\nAftale-\/forsikringsnummer\n\nEvt. bem\u00e6rkninger\n\nForsikringsselskabets navn og adresse\n\nKontaktperson\n\nDato og underskrift\n\nSP 216 (05\/2011)\nUdarbejdet af KL\n\nKommuneinformation\nSide 3 af 5\n\n\fUddrag af lov om retssikkerhed og administration p\u00e5 det sociale omr\u00e5de\n(Retssikkerhedsloven)\n\u00a7 11. Myndigheden kan anmode personer, der s\u00f8ger\nom eller f\u00e5r hj\u00e6lp, om\n1) at medvirke til at f\u00e5 de oplysninger frem, som er n\u00f8dvendige for at afg\u00f8re, hvilken hj\u00e6lp de er berettiget til,\nog\n2) at lade sig unders\u00f8ge hos en l\u00e6ge eller blive indlagt\ntil observation og behandling som led i sagsbehandlingen.\nStk. 2. Personer, der f\u00e5r hj\u00e6lp, har pligt til at oplyse om\n\u00e6ndringer, der kan have betydning for hj\u00e6lpen.\n\u00a7 11a. Myndigheden kan efter forudg\u00e5ende samtykke\nfra den, der s\u00f8ger om eller f\u00e5r hj\u00e6lp, forlange, at andre\noffentlige myndigheder, uddannelsesinstitutioner, sygehuse, l\u00e6ger, psykologer, autoriserede sundhedspersoner i \u00f8vrigt og personer, der handler p\u00e5 disses ansvar,\narbejdsl\u00f8shedskasser, pengeinstitutter, arbejdsgivere\nog private, der udf\u00f8rer opgaver for det offentlige, giver\noplysninger om den p\u00e5g\u00e6ldende, der er n\u00f8dvendige for\nat behandle sagen. Dette g\u00e6lder ogs\u00e5 oplysninger om en\npersons rent private forhold og andre fortrolige oplysninger, ligesom myndigheden kan indhente l\u00e6gejournaler,\nsygehusjournaler eller udskrifter heraf. Myndigheden kan\nforlange, at der optages retsligt forh\u00f8r i overensstemmelse med retsplejelovens \u00a7 1018, hvis oplysningerne\nikke videregives.\nStk. 2. Myndigheden kan uden samtykke til brug for\nbehandlingen af en enkelt sag eller til brug for generel\nkontrol kr\u00e6ve oplysninger om \u00f8konomiske forhold om\nden, der ans\u00f8ger om eller f\u00e5r hj\u00e6lp, og dennes \u00e6gtef\u00e6lle\neller samlever, fra andre offentlige myndigheder samt fra\narbejdsl\u00f8shedskasser. Tilsvarende oplysninger kan indhentes om andre husstandsmedlemmer. Oplysninger kan\nsamk\u00f8res og sammenstilles med data fra myndighedens\negne, andre myndigheders og arbejdsl\u00f8shedskassers itsystemer, n\u00e5r dette er n\u00f8dvendigt for at kontrollere, om\nbetingelserne for at yde hj\u00e6lp er opfyldt, herunder med\nhenblik p\u00e5 efterf\u00f8lgende kontrol af, om der er sket fejl eller\nmisbrug i forbindelse med ydelse af hj\u00e6lp. Oplysningerne\nkan indhentes, selv om den person, som oplysningerne\nvedr\u00f8rer, ikke bor i den kommune, som indhenter oplysningerne.\nStk. 3. Kommunalbestyrelsen kan uden samtykke fra\nborgeren forlange at f\u00e5 n\u00f8dvendige oplysninger om \u00f8konomiske forhold fra pengeinstitutter og arbejdsgivere til\nbrug for stikpr\u00f8vekontrol i sager efter lov om social pension og lov om h\u00f8jeste, mellemste, forh\u00f8jet almindelig\nog almindelig f\u00f8rtidspension m.v. med henblik p\u00e5 at kontrollere pensionistens indkomst- og formueforhold. Oplysningerne kan sammenstilles med \u00f8vrige oplysninger om\n\u00f8konomiske forhold, som kommunen er i besiddelse af\nmed henblik p\u00e5 kontrol af, om der er sket misbrug i forbindelse med udbetaling af social pension.\nStk. 4. Myndigheden kan f\u00e5 terminaladgang til de\nn\u00f8dvendige oplysninger som n\u00e6vnt i stk. 1 og 2 i ind-\n\nkomstregisteret, jf. \u00a7 7 i lov om et indkomstregister. I det\nomfang oplysningerne som n\u00e6vnt i stk. 1 eller 2 findes i\nindkomstregisteret, skal myndigheden indhente oplysningerne herfra.\nStk. 5 (Udeladt).\n\u00a7 11b. Hvis borgeren ikke medvirker, jf. \u00a7 11, stk. 1, nr.\n1 og 2, eller ikke giver samtykke til, at myndigheden kan\nindhente oplysninger, jf. \u00a7 11a, stk. 1, skal myndigheden\nbehandle sagen om hj\u00e6lp p\u00e5 det foreliggende grundlag,\nmedmindre oplysningerne kan indhentes uden samtykke,\njf. \u00a7 11a, stk. 2, og \u00a7 11c.\n\u00a7 11c. Hvis det er n\u00f8dvendigt for sagens behandling,\nkan kravet om samtykke efter \u00a7 11 a, stk. 1 og 5, fraviges\ni sager om\n1) (udeladt),\n2) f\u00f8rtidspension, hvor myndigheden kan p\u00e5begynde en\nsag eller tr\u00e6ffe afg\u00f8relse i en sag, uden af den p\u00e5g\u00e6ldende person selv har rettet henvendelse herom, jf.\n\u00a7 17, stk. 2, i lov om social pension,\n3) frakendelse af f\u00f8rtidspension, jf. \u00a7 44, stk. 1, i lov om\nsocial pension, og frakendelse eller overflytning til\nanden pension, jf. \u00a7 44, stk. 1, i lov om h\u00f8jeste, mellemste, forh\u00f8jet almindelig og almindelig f\u00f8rtidspension\nm.v.,\n4)-5) (udeladt).\nStk. 2-4. (Udeladt).\n\u00a7 12a. Kommunen har til enhver tid uden retskendelse\nadgang til en virksomheds lokaler m.v. samt p\u00e5 arbejdssteder uden for virksomhedens lokaler med henblik p\u00e5 at\nkontrollere de oplysninger om borgernes l\u00f8n- og arbejdsforhold, som ligger til grund for udbetaling af ydelser i\nsager, der er omfattet af denne lov, jf. \u00a7 2, stk. 4. Det er\nden kommune, som virksomheden ligger i, der kan foretage kontrollen. Kommunen har ikke uden retskendelse\nadgang til at foretage kontrollen i private hjem.\nStk. 2-7. (Udeladt).\nStk. 8. Personer, der er besk\u00e6ftiget i virksomheden ved\neftersynet, kan anmodes om at oplyse navn, adresse og\nf\u00f8dselsdato, ans\u00e6ttelsesperiode og l\u00f8n- og ans\u00e6ttelsesvilk\u00e5r, samt om de aktuelt modtager sociale eller besk\u00e6ftigelsesm\u00e6ssige ydelser.\nStk. 9. (Udeladt).\n\u00a7 12b. Medmindre h\u00f8jere straf kan id\u00f8mmes efter anden\nlovgivning, straffes med b\u00f8de den, der ved grov uagtsomhed fremkalder, bestyrker eller udnytter en vildfarelse hos\nmyndigheden ved at afgive urigtige eller vildledende oplysninger eller ved at undlade at give oplysninger om forhold,\nder har betydning for hj\u00e6lpen, jf. \u00a7 11, stk. 1, nr. 1, og stk.\n2, og derved p\u00e5f\u00f8rer myndigheden et formuetab.\nStk. 2-3. (Udeladt).\n\nSP 216 (05\/2011)\nUdarbejdet af KL\n\nKommuneinformation\nSide 4 af 5\n\n\fDen Supplerende Arbejdsmarkedspension\nfor f\u00f8rtidspensionister (2011)\nVil du spare mere op til pension\nSom f\u00f8rtidspensionist har du mulighed for at indbetale til den Supplerende Arbejdsmarkedspension.\nDen Supplerende Arbejdsmarkedspension er et livsvarigt supplement til din folkepension, som kan v\u00e6re\nmed til at g\u00f8re overgangen fra f\u00f8rtidspension til folkepension lettere.\nPensionen kan udbetales, n\u00e5r du n\u00e5r folkepensionsalderen. Den udbetalte pension er skattepligtig.\nPensionens st\u00f8rrelse afh\u00e6nger af, hvor meget der er\nindbetalt, og hvor stor forrentningen har v\u00e6ret.\n\nHvad koster det\nDet m\u00e5nedlige bidrag er 459 kr. (g\u00e6ldende i 2011).\nDu skal selv betale en tredjedel, alts\u00e5 (153 kr.), mens\nstaten betaler de resterende to tredjedele (306 kr.).\nBidraget medregnes ikke i din skattepligtige indkomst. Det betyder, at din andel p\u00e5 153 kr. fratr\u00e6kkes\ndin f\u00f8rtidspension, f\u00f8r der beregnes skat.\nBidraget reguleres ligesom din f\u00f8rtidspension en\ngang om \u00e5ret.\n\nHvor kan bel\u00f8bet indbetales\nDu kan v\u00e6lge at f\u00e5 bel\u00f8bet indbetalt til ATP, et livsforsikringsselskab eller en pensionskasse. Det er dog\nikke alle livsforsikringsselskaber og pensionskasser,\nder modtager indbetaling til den Supplerende Arbejdsmarkedspension. Hvis du \u00f8nsker at indbetale til\net livsforsikringsselskab eller en pensionskasse, skal\ndu kontakte selskabet p\u00e5 forh\u00e5nd og h\u00f8re, om det er\nmuligt. Du har dog altid mulighed for at indbetale til\nATP.\nN\u00e5r du er tilmeldt ordningen, indbetaler din kommune automatisk det samlede bidrag til det pensionsinstitutet (ATP, livsforsikringsselskab eller pensionskasse), du har valgt.\nIndbetalingen oph\u00f8rer automatisk ved folkepensionsalderen.\n\nBetaling af arbejdsmarkedsbidrag\nDa der er tale om en arbejdsmarkedspension, tr\u00e6kker pensionsinstituttet arbejdsmarkedsbidrag af \u00e5rets\nsamlede indbetalte bidrag.\n\nHvis du v\u00e6lger at indbetale til ATP, tr\u00e6der ordningen\ni kraft med det samme. Hvis du har valgt, at ordningen skal administreres i et livsforsikringsselskab eller\nen pensionskasse, vil kommunen videresende din tilmelding til godkendelse i det p\u00e5g\u00e6ldende livsforsikringsselskab eller pensionskasse.\nDu kan selv v\u00e6lge fra hvilket tidspunkt, du \u00f8nsker at\nindtr\u00e6de i ordningen.\n\nUdmeldelse og skift af pensionsinstitut\n(ATP, livsforsikringsselskab eller pensionskasse)\nDu kan altid udmelde dig af den Supplerende Arbejdsmarkedspension igen, eller skifte til et andet\npensionsinstitut.\nUdtr\u00e6den af ordningen eller skift til andet pensionsinstitut vil ske den 1. i m\u00e5neden, efter der er g\u00e5et en\nm\u00e5ned, fra du har givet kommunen meddelelse herom.\n\nSkilsmisse\nDin Supplerende Arbejdsmarkedspension skal ikke\ndeles i forbindelse med skilsmisse.\n\nD\u00f8dsfald\nHvis du d\u00f8r, f\u00f8r du er fyldt 65 \u00e5r, standser indbetalingen med virkning fra den 1. i m\u00e5neden efter d\u00f8dsfaldet.\nHvis du havde ordningen p\u00e5 s\u00e6rskilt konto i ATP, udbetales indest\u00e5endet p\u00e5 kontoen til boet.\nHvis du havde ordningen i et livsforsikringsselskab\neller en pensionskasse, udbetales v\u00e6rdien af den\nerhvervede pensionsret til boet eller til den begunstigede if\u00f8lge pensionsaftalen.\nRetten til at f\u00e5 udbetalt bel\u00f8b i forbindelse med d\u00f8dsfald bortfalder, n\u00e5r du er fyldt 65 \u00e5r.\n\nYderligere information\nDu kan l\u00e6se mere om ordningen hos ATP p\u00e5\nwww.atp.dk\n\u00d8nsker du yderligere information om ordningen hos\net livsforsikringsselskab eller en pensionskasse, kan\ndu f\u00e5 det p\u00e5 selskabets hjemmeside eller ved at kontakte selskabet.\n\nTilmelding\nTilmelding til ordningen er frivillig.\nHvis du vil deltage i ordningen, skal du udfylde en\ntilmeldingsblanket og sende eller aflevere den til din\nkommune.\nSP 216 (05\/2011)\nUdarbejdet af KL\n\nKommuneinformation\nSide 5 af 5\n\n\f"}