{"classes":[{"id":"88.00.00","title":"Kommunens indk\u00f8b og udbud i almindelighed"}],"title":"EU-udbud p\u00e5 befordring af elever til specialskoler og specialklasser i Syddjurs Kommune ","text":" Syddjurs Kommune afholder EU-udbud p\u00e5 k\u00f8rsel. Den udbudte k\u00f8rsel omfatter fast k\u00f8rsel af visiterede elever til og fra specialskoler og specialklasser i Syddjurs Kommune med opstart august 2014. Kontraktperioden for den udbudte k\u00f8rsel er 3 \u00e5r. Tilbudsfrist: d. 15. maj 2014 Udbudsmaterialet kan rekvireres ved skriftlig henvendelse til Klaus Dannemarre p\u00e5 klds@syddjurs.dk \n\n"}