{"classes":[{"id":"84.00.00","title":"Offentlige valg i almindelighed"}],"title":"Opstillingsberettigede partier og lister","text":" Kandidatlister og listeforbund \/ valgforbund Kandidatlister og anmeldelse af listeforbund og\/eller valgforbund til kommunalvalget den 19. november 2013 kan rekvireres hos Direktionssekretariatet, Lundbergsvej 2, 8400 Ebeltoft tlf.nr. 87 53 50 10 eller e-mail direktionssekretariat@syddjurs.dk Kandidatlister skal afleveres til formanden for valgbestyrelsen p\u00e5 adressen Direktionssekretariatet, Lundbergsvej 2, 8400 Ebeltoft i tidsrummet fra tirsdag den 8. oktober 2013 og skal afleveres senest tirsdag den 22. oktober 2013 kl. 12.00. Kandidatlisten skal v\u00e6re underskrevet af mindst 25 og h\u00f8jest 50 v\u00e6lgere i kommunen som stillere. Kandidatlister kan, for valgbestyrelsen, anmelde at ville st\u00f8tte hinanden (valgforbund og\/eller listeforbund). Anmeldelse af valgforbund og\/eller listeforund skal ske skriftligt senest mandag den 28. oktober 2013 kl. 12.00 og afleveres til formanden for valgbestyrelsen p\u00e5 adressen Direktionssekretariatet, Lundbergsvej 2, 8400 Ebeltoft. Anmeldelsen skal v\u00e6re underskrevet af alle listens stillere og kandidater. Stillere og kandidater kan imidlertid p\u00e5 anmeldelsen af kandidatlisten skriftligt bemyndige en eller flere stillere eller kandidater til at anmelde valgforbund og\/eller listeforbund. \n\n"}