{"classes":[{"id":"13.06.02","title":"Salg af jord"}],"title":"Pindstrup","text":" Priserne er\u00a0inkl. tilslutningsafgifter til\u00a0el og kloak. Grundene i Pindstrup s\u00e6lges\u00a0gennem f\u00f8lgende ejendomsm\u00e6glere: \u00a0 Estate M\u00e6glerne, S\u00f8ndergade 8, 8560 Kolind, tlf 86 39 28 88 RealM\u00e6glerne Ryomgaard, Slotsgade 5, 8550 Ryomg\u00e5rd, tlf. 863 9 42 00 Kort: \u00c5ben kort med priser i eget vindue Bem\u00e6rk at reserverede grunde markeret med gult ikke er solgte, men reserverede uden fork\u00f8bsret. Se mere om betingelser for reservation under FAQ Fotos: se billeder her Pindstrup: I hyggelig landsby t\u00e6t p\u00e5 Ryomg\u00e5rd, ligger udstykningen fredeligt tilbagetrukket fra hovedvejen. Her kan man f\u00e5 en meget billig byggegrund t\u00e6t p\u00e5 fantastisk naturomr\u00e5de og gr\u00e6nsende op til skoven og lige overfor idr\u00e6tshallen. Der er indk\u00f8bsmuligheder i Pindstrup. Skoleb\u00f8rn h\u00f8rer under Marienhoffskolen i Ryomg\u00e5rd. Der g\u00e5r skolebus. T\u00f8rvevej 2, 4, 6 og 12: Grundene ligger p\u00e5\u00a0en sidevej til Brunmosevej og er beliggende p\u00e5 hhv. h\u00f8jre og venstre side af indk\u00f8rslen samt i \"bunden\" af udstykningen. Bag udstykningen er et nyere kvarter. I l\u00e6 af skoven og bakken bag ved ligger grundene fredeligt og solrigt lige ud til naturen og alligevel er der blot 100 m. til Pindstrup Hallen, som ligger p\u00e5 en anden sidevej til Brunmosevej men p\u00e5 modsatte side, og\u00a0 ca. 200 meter til den integrerede\u00a0institution Margretheb\u00f8rnehaven. Materiale Se samlet materiale (M\u00e5leblad, betingelser, tingbogsattest, servitutter etc.) (M\u00e5leblad, betingelser, tingbogsattest, servitutter etc.) Yderligere oplysninger kan f\u00e5s ved henvendelse til Syddjurs Kommune. \n\n"}