{"classes":[{"id":"00.22.00","title":"Kommunalbestyrelsen, udvalg mv. - kommuners styrelse i almindelighed"}],"title":"Video fra byr\u00e5det","text":" You need a browser that can handle Iframes to be able to view this page. Transmissionen starter ca. 10 minutter inden m\u00f8dets start. Klik p\u00e5 video billedet for at starte. Byr\u00e5dsm\u00f8de onsdag den 25. juni 2014 kl. 16.00 Dagsorden \/ Referat med video Se fuld dagsorden med sagsbeskrivelser og bilag i vores dagsordenssystem her Referatet er tilg\u00e6ngeligt online i l\u00f8bet af dagen efter m\u00f8det. Punkt 155 Sp\u00f8rgetid 25\/6-14 Punkt 156 Forslag fra Enhedslisten: ans\u00f8gning om forh\u00f8jelse af kommuneskatten Punkt 157 Skaf\u00f8g\u00e5rd. Ans\u00f8gning om planl\u00e6gning for 3 vindm\u00f8ller Punkt 158 Landsbypuljen 2015. Ans\u00f8gning om andel i Pulje Punkt 159 Syddjurs Kommuneplan 2013. Till\u00e6g nr. 6. Endelig behandling Punkt 160 Kolind+. Kultur og Idr\u00e6tscenter med Bibliotek, Idr\u00e6tsfaciliteter, Lokalarkiv og Folkeoplysende lokaler Punkt 161 Affaldsplan 2014 - 2024 - Godkendelse af forslag Punkt 162 Regulativ for jordstyring - Omr\u00e5deklassificering Punkt 163 Kvalitetsstandarder Punkt 164 L\u00e6seplan vedr. kriminalitetsforebyggende emner Punkt 165 Anl\u00e6gsbevilling til ombygning af administrationsbygninger Punkt 166 Investering p\u00e5 besk\u00e6ftigelsesomr\u00e5det i Syddjurs Kommune Punkt 167 \u00c5rsregnskab 2013 for Det F\u00e6lleskommunale Redningsberedskab Punkt 168 Skema B for 24 familieboliger i Nannas V\u00e6nge i Hornslet Punkt 169 Budgetopf\u00f8lgning pr. 30. april 2014 - \u00d8konomiudvalgets omr\u00e5de Punkt 170 Budgetopf\u00f8lgning pr. 30. april 2014 - Familie og Institutioner Punkt 171 Budgetopf\u00f8lgning pr. 30. april 2014 - Udvalget for Natur, teknik og milj\u00f8 Punkt 172 Budgetopf\u00f8lgning pr. 30. april 2014 - Udvalget for sundhed, \u00e6ldre og social Punkt 173 Budgetopf\u00f8lgning pr. 30. april 2014 - Udvalget for plan, udvikling og kultur Punkt 174 Budgetopf\u00f8lgning pr. 30. april 2014 - Arbejdsmarked Punkt 175 Resultatrevision 2013 Punkt 176 Ministeriet for B\u00f8rn, Ligestilling, Integration og Sociale Forhold - decisionsskrivelse for regnskabs\u00e5ret 2012 - Revisionsberetning nr. 17 Punkt 177 Byfornyelsesprogram for Omr\u00e5defornyelse af M\u00f8rke Bymidte. Tilsagn om st\u00f8tte og godkendelse Punkt 178 Landdistriktspuljen 2014. Nyt Lys i M\u00f8rke. Tilskud \n\n"}